niagads/arg_parser/__init__.py
niagads/arg_parser/core.py
niagads/csv_parser/__init__.py
niagads/csv_parser/core.py
niagads/csv_validator/__init__.py
niagads/csv_validator/core.py
niagads/enums/common.py
niagads/enums/core.py
niagads/excel_parser/__init__.py
niagads/excel_parser/core.py
niagads/exceptions/__init__.py
niagads/exceptions/core.py
niagads/json_validator/__init__.py
niagads/json_validator/core.py
niagads/json_validator/custom_validators.py
niagads/json_validator/format_checkers.py
niagads/metadata_validator/README.md
niagads/metadata_validator/__init__.py
niagads/metadata_validator/core.py
niagads/metadata_validator_tool/README.md
niagads/metadata_validator_tool/__init__.py
niagads/metadata_validator_tool/core.py
niagads/utils/__init__.py
niagads/utils/dict.py
niagads/utils/list.py
niagads/utils/logging.py
niagads/utils/numeric.py
niagads/utils/pandas.py
niagads/utils/regular_expressions.py
niagads/utils/string.py
niagads/utils/sys.py
niagads_metadata_validator-0.2.3.dist-info/METADATA
niagads_metadata_validator-0.2.3.dist-info/WHEEL
niagads_metadata_validator-0.2.3.dist-info/entry_points.txt
niagads_metadata_validator-0.2.3.dist-info/RECORD
