Metadata-Version: 2.4
Name: niagads-metadata-validator
Version: 0.2.3
Summary: JSON Schema based validation of dataset metadata developed to support submissions to the NIAGADS Data Sharing Service
License: GNU GPLv3
Author: fossilfriend
Author-email: egreenfest@gmail.com
Requires-Python: >=3.10,<4.0
Classifier: License :: Other/Proprietary License
Classifier: Programming Language :: Python :: 3
Classifier: Programming Language :: Python :: 3.10
Classifier: Programming Language :: Python :: 3.11
Classifier: Programming Language :: Python :: 3.12
Classifier: Programming Language :: Python :: 3.13
Classifier: Programming Language :: Python :: 3.14
Requires-Dist: jsonschema (>=4.23.0,<5.0.0)
Requires-Dist: openpyxl (>=3.1.5,<4.0.0)
Requires-Dist: pandas (>=2.2.3,<3.0.0)
Requires-Dist: pydantic (>=2.11.3,<3.0.0)
Requires-Dist: python-dateutil (>=2.9.0.post0,<3.0.0)
Requires-Dist: strenum (>=0.4.15,<0.5.0)
Project-URL: Bug Reports, https://github.com/NIAGADS/niagads-pylib/issues
Project-URL: Homepage, https://github.com/NIAGADS/niagads-pylib
Project-URL: Source, https://github.com/NIAGADS/niagads-pylib
